swankit/__init__.py
swankit/env.py
swankit/callback/__init__.py
swankit/callback/models/__init__.py
swankit/callback/models/error.py
swankit/callback/models/key.py
swankit/callback/models/runtime.py
swankit/core/__init__.py
swankit/core/data.py
swankit/core/settings.py
swankit/log/__init__.py
swankit/log/log.py
swankit/log/utils.py
swankit-0.2.4.dist-info/METADATA
swankit-0.2.4.dist-info/WHEEL
swankit-0.2.4.dist-info/licenses/LICENSE
swankit-0.2.4.dist-info/RECORD
